{".class": "MypyFile", "_fullname": "usr", "is_partial_stub_package": false, "is_stub": false, "names": {".class": "SymbolTable", "Path": {".class": "SymbolTableNode", "cross_ref": "pathlib.Path", "kind": "Gdef"}, "__doc__": {".class": "SymbolTableNode", "kind": "Gdef", "node": {".class": "Var", "flags": ["is_ready"], "fullname": "usr.__doc__", "name": "__doc__", "type": "builtins.str"}}, "__file__": {".class": "SymbolTableNode", "kind": "Gdef", "node": {".class": "Var", "flags": ["is_ready"], "fullname": "usr.__file__", "name": "__file__", "type": "builtins.str"}}, "__name__": {".class": "SymbolTableNode", "kind": "Gdef", "node": {".class": "Var", "flags": ["is_ready"], "fullname": "usr.__name__", "name": "__name__", "type": "builtins.str"}}, "__package__": {".class": "SymbolTableNode", "kind": "Gdef", "node": {".class": "Var", "flags": ["is_ready"], "fullname": "usr.__package__", "name": "__package__", "type": "builtins.str"}}, "_getVars": {".class": "SymbolTableNode", "kind": "Gdef", "node": {".class": "FuncDef", "arg_kinds": [], "arg_names": [], "flags": [], "fullname": "usr._getVars", "name": "_getVars", "type": null}}, "defaultVals": {".class": "SymbolTableNode", "kind": "Gdef", "node": {".class": "FuncDef", "arg_kinds": [], "arg_names": [], "flags": [], "fullname": "usr.defaultVals", "name": "defaultVals", "type": null}}, "json": {".class": "SymbolTableNode", "cross_ref": "json", "kind": "Gdef"}, "load": {".class": "SymbolTableNode", "kind": "Gdef", "node": {".class": "FuncDef", "arg_kinds": [0, 0], "arg_names": ["path", "session"], "flags": [], "fullname": "usr.load", "name": "load", "type": {".class": "CallableType", "arg_kinds": [0, 0], "arg_names": ["path", "session"], "arg_types": ["pathlib.Path", {".class": "AnyType", "missing_import_name": null, "source_any": null, "type_of_any": 1}], "bound_args": [], "def_extras": {"first_arg": null}, "fallback": "builtins.function", "implicit": false, "is_ellipsis_args": false, "name": "load", "ret_type": {".class": "AnyType", "missing_import_name": null, "source_any": null, "type_of_any": 1}, "variables": []}}}, "os": {".class": "SymbolTableNode", "cross_ref": "os", "kind": "Gdef"}, "settings": {".class": "SymbolTableNode", "kind": "Gdef", "node": {".class": "TypeInfo", "_promote": null, "abstract_attributes": [], "bases": ["builtins.object"], "declared_metaclass": null, "defn": {".class": "ClassDef", "fullname": "usr.settings", "name": "settings", "type_vars": []}, "flags": [], "fullname": "usr.settings", "metaclass_type": null, "metadata": {}, "module_name": "usr", "mro": ["usr.settings", "builtins.object"], "names": {".class": "SymbolTable", "DATASET_ID": {".class": "SymbolTableNode", "kind": "Mdef", "node": {".class": "Var", "flags": ["is_initialized_in_class", "is_ready"], "fullname": "usr.settings.DATASET_ID", "name": "DATASET_ID", "type": "builtins.str"}}, "DV_DATASET_ID": {".class": "SymbolTableNode", "kind": "Mdef", "node": {".class": "Var", "flags": ["is_initialized_in_class", "is_ready"], "fullname": "usr.settings.DV_DATASET_ID", "name": "DV_DATASET_ID", "type": "builtins.str"}}, "DV_FILE_ID": {".class": "SymbolTableNode", "kind": "Mdef", "node": {".class": "Var", "flags": ["is_initialized_in_class", "is_ready"], "fullname": "usr.settings.DV_FILE_ID", "name": "DV_FILE_ID", "type": "builtins.str"}}, "DV_KEY": {".class": "SymbolTableNode", "kind": "Mdef", "node": {".class": "Var", "flags": ["is_initialized_in_class", "is_ready"], "fullname": "usr.settings.DV_KEY", "name": "DV_KEY", "type": "builtins.str"}}, "DV_KEY_MASKED": {".class": "SymbolTableNode", "kind": "Mdef", "node": {".class": "Var", "flags": ["is_initialized_in_class", "is_ready"], "fullname": "usr.settings.DV_KEY_MASKED", "name": "DV_KEY_MASKED", "type": "builtins.str"}}, "GLOBUS_ENDPOINTS": {".class": "SymbolTableNode", "kind": "Mdef", "node": {".class": "Var", "flags": ["is_initialized_in_class", "is_ready"], "fullname": "usr.settings.GLOBUS_ENDPOINTS", "name": "GLOBUS_ENDPOINTS", "type": "builtins.str"}}, "GLOBUS_ID": {".class": "SymbolTableNode", "kind": "Mdef", "node": {".class": "Var", "flags": ["is_initialized_in_class", "is_ready"], "fullname": "usr.settings.GLOBUS_ID", "name": "GLOBUS_ID", "type": "builtins.str"}}, "GLOBUS_USER": {".class": "SymbolTableNode", "kind": "Mdef", "node": {".class": "Var", "flags": ["is_initialized_in_class", "is_ready"], "fullname": "usr.settings.GLOBUS_USER", "name": "GLOBUS_USER", "type": "builtins.str"}}, "LAB_ID": {".class": "SymbolTableNode", "kind": "Mdef", "node": {".class": "Var", "flags": ["is_initialized_in_class", "is_ready"], "fullname": "usr.settings.LAB_ID", "name": "LAB_ID", "type": "builtins.str"}}, "SRC_ENDPOINT": {".class": "SymbolTableNode", "kind": "Mdef", "node": {".class": "Var", "flags": ["is_initialized_in_class", "is_ready"], "fullname": "usr.settings.SRC_ENDPOINT", "name": "SRC_ENDPOINT", "type": "builtins.str"}}}, "tuple_type": null, "type_vars": [], "typeddict_type": null}}, "updateDisk": {".class": "SymbolTableNode", "kind": "Gdef", "node": {".class": "FuncDef", "arg_kinds": [0, 0], "arg_names": ["path", "session"], "flags": [], "fullname": "usr.updateDisk", "name": "updateDisk", "type": {".class": "CallableType", "arg_kinds": [0, 0], "arg_names": ["path", "session"], "arg_types": ["pathlib.Path", {".class": "AnyType", "missing_import_name": null, "source_any": null, "type_of_any": 1}], "bound_args": [], "def_extras": {"first_arg": null}, "fallback": "builtins.function", "implicit": false, "is_ellipsis_args": false, "name": "updateDisk", "ret_type": {".class": "AnyType", "missing_import_name": null, "source_any": null, "type_of_any": 1}, "variables": []}}}}, "path": "c:\\Dropbox\\data\\AbleAntDesign\\Clients\\KState\\CNAP\\synapse-globus\\usr.py"}